ddge/__init__.py
ddge/__main__.py
ddge/api.py
ddge/cli.py
ddge/storage.py
ddge-0.2.137.4.dist-info/licenses/LICENSE
ddge-0.2.137.4.dist-info/METADATA
ddge-0.2.137.4.dist-info/WHEEL
ddge-0.2.137.4.dist-info/entry_points.txt
ddge-0.2.137.4.dist-info/top_level.txt
ddge-0.2.137.4.dist-info/RECORD
