Metadata-Version: 2.4
Name: ddge
Version: 0.2.137.4
Summary: DuckDuckGo Email Protection CLI
Home-page: https://github.com/lzgirlcat/ddge
Author: Zoey !
Maintainer-email: cb98uzhd@duck.com
License: GNU General Public License v3.0
Project-URL: Source (GitHub), https://github.com/lzgirlcat/ddge
Project-URL: Issue Tracker, https://github.com/lzgirlcat/ddge/issues
Keywords: email,duckdcukgo,protection,ddg
Classifier: Programming Language :: Python :: 3
Classifier: Operating System :: OS Independent
Requires-Python: >=3.7
License-File: LICENSE
Requires-Dist: requests
Requires-Dist: rich
Dynamic: author
Dynamic: classifier
Dynamic: description
Dynamic: description-content-type
Dynamic: home-page
Dynamic: keywords
Dynamic: license
Dynamic: license-file
Dynamic: maintainer-email
Dynamic: project-url
Dynamic: requires-dist
Dynamic: requires-python
Dynamic: summary
